otterdog/__init__.py
otterdog/cache.py
otterdog/cli.py
otterdog/config.py
otterdog/credentials/__init__.py
otterdog/credentials/bitwarden_provider.py
otterdog/credentials/inmemory_provider.py
otterdog/credentials/pass_provider.py
otterdog/credentials/plain_provider.py
otterdog/jsonnet.py
otterdog/logging.py
otterdog/models/__init__.py
otterdog/models/branch_protection_rule.py
otterdog/models/custom_property.py
otterdog/models/environment.py
otterdog/models/github_organization.py
otterdog/models/organization_role.py
otterdog/models/organization_ruleset.py
otterdog/models/organization_secret.py
otterdog/models/organization_settings.py
otterdog/models/organization_variable.py
otterdog/models/organization_webhook.py
otterdog/models/organization_workflow_settings.py
otterdog/models/repo_ruleset.py
otterdog/models/repo_secret.py
otterdog/models/repo_variable.py
otterdog/models/repo_webhook.py
otterdog/models/repo_workflow_settings.py
otterdog/models/repository.py
otterdog/models/role.py
otterdog/models/ruleset.py
otterdog/models/secret.py
otterdog/models/team.py
otterdog/models/variable.py
otterdog/models/webhook.py
otterdog/models/workflow_settings.py
otterdog/operations/__init__.py
otterdog/operations/apply.py
otterdog/operations/approve_blueprints.py
otterdog/operations/canonical_diff.py
otterdog/operations/check_status.py
otterdog/operations/check_token_permissions.py
otterdog/operations/delete_file.py
otterdog/operations/diff_operation.py
otterdog/operations/dispatch_workflow.py
otterdog/operations/fetch_config.py
otterdog/operations/import_configuration.py
otterdog/operations/install_app.py
otterdog/operations/list_advisories.py
otterdog/operations/list_apps.py
otterdog/operations/list_blueprints.py
otterdog/operations/list_members.py
otterdog/operations/list_projects.py
otterdog/operations/local_apply.py
otterdog/operations/local_plan.py
otterdog/operations/open_pull_request.py
otterdog/operations/plan.py
otterdog/operations/push_config.py
otterdog-1.1.0.dist-info/LICENSE
otterdog-1.1.0.dist-info/METADATA
otterdog-1.1.0.dist-info/WHEEL
otterdog-1.1.0.dist-info/entry_points.txt
otterdog-1.1.0.dist-info/RECORD
