Metadata-Version: 2.3
Name: otterdog
Version: 1.1.0
Summary: Tool to manage GitHub organizations and their repositories.
License: EPL-2.0
Keywords: infrastructure-as-code,supply-chain-security,github,gitops
Author: Thomas Neidhart
Author-email: thomas.neidhart@eclipse-foundation.org
Requires-Python: >=3.11,<4.0
Classifier: Development Status :: 5 - Production/Stable
Classifier: Environment :: Console
Classifier: Intended Audience :: Developers
Classifier: Intended Audience :: System Administrators
Classifier: License :: OSI Approved :: Eclipse Public License 2.0 (EPL-2.0)
Classifier: Programming Language :: Python
Classifier: Programming Language :: Python :: 3
Classifier: Programming Language :: Python :: 3.11
Classifier: Programming Language :: Python :: 3.12
Classifier: Programming Language :: Python :: 3.13
Classifier: Topic :: Security
Classifier: Topic :: Software Development :: Version Control
Classifier: Topic :: System :: Systems Administration
Classifier: Typing :: Typed
Requires-Dist: GitPython (>=3.1,<4.0)
Requires-Dist: JSONBender (>=0.9,<1.0)
Requires-Dist: PyNaCl (>=1.5,<2.0)
Requires-Dist: aiofiles (>=24.1,<25.0)
Requires-Dist: aiohttp (>=3.11,<4.0.0)
Requires-Dist: aiohttp-client-cache (>=0.12.3,<1.0.0)
Requires-Dist: aiohttp-retry (>=2.9,<3.0)
Requires-Dist: aioshutil (>=1.5,<2.0)
Requires-Dist: aiosqlite (>=0.20,<1.0)
Requires-Dist: asyncer (>=0.0.8,<1.0)
Requires-Dist: chevron (>=0.14,<1.0)
Requires-Dist: click (>=8.1,<9.0)
Requires-Dist: importlib_resources (>=6.4,<7.0)
Requires-Dist: jsonata-python (>=0.5,<1.0)
Requires-Dist: jsonschema (>=4.23,<5.0)
Requires-Dist: jwt (>=1.3,<2.0)
Requires-Dist: mintotp (>=0.3,<1.0)
Requires-Dist: playwright (>=1.44,<2.0)
Requires-Dist: requests (>=2.32,<3.0)
Requires-Dist: rich (>=13.9,<14.0)
Requires-Dist: rjsonnet (>=0.5,<1.0)
Project-URL: Changelog, https://github.com/eclipse-csi/otterdog/blob/main/CHANGELOG.md
Project-URL: Documentation, https://otterdog.readthedocs.io
Project-URL: Homepage, https://github.com/eclipse-csi/otterdog
Project-URL: Repository, https://github.com/eclipse-csi/otterdog
